sejm_api.py
sejmapi-0.1.0.dist-info/LICENSE
sejmapi-0.1.0.dist-info/METADATA
sejmapi-0.1.0.dist-info/WHEEL
sejmapi-0.1.0.dist-info/top_level.txt
sejmapi-0.1.0.dist-info/RECORD
