Metadata-Version: 2.1
Name: sejmapi
Version: 0.1.0
Summary: UNKNOWN
Home-page: https://github.com/KomarJazdek/Your-First-Python-Package-on-PyPI
Author: Michal Salamon
Author-email: komarjazdek23@gmail.com
License: UNKNOWN
Keywords: API,Sejm,Government
Platform: UNKNOWN
Classifier: Development Status :: 4 - Beta
Classifier: Programming Language :: Python :: 3
Classifier: Programming Language :: Python :: 3.6
Classifier: Programming Language :: Python :: 3.7
Classifier: Programming Language :: Python :: 3.8
Classifier: Programming Language :: Python :: 3.9
Classifier: License :: OSI Approved :: BSD License
Classifier: Intended Audience :: Developers
Classifier: Intended Audience :: Other Audience
Classifier: Intended Audience :: Science/Research
Classifier: Intended Audience :: Education
Classifier: Topic :: Text Processing
Classifier: Operating System :: Microsoft :: Windows
Classifier: Operating System :: OS Independent
Requires-Dist: requests (~=2.31.0)
